{
    "authorNames" : ["懂球帝", "先进生产力", "夹练成厨", "涨姿势", "不知道放哪儿", "大像", "时光碎片", "Tesla 中国","程查", "译文", "沥青", "成武", "王强", "诸葛", "慕青", "任家", "陈静", "王五","孟小白","顿雨婷","喃","揭妤","夜叶","石亚琼","张耘溪","张雨忻"],
    
    "subjects" : ["[视频]骑士绝地反击屠杀勇士 鹿死谁手尤...",
                  "[创意]中关村的广告牌掉下来",
                  "[美食]囿于昼夜，厨房与爱",
                  "[图集]要提高自己的姿势水平 生命更多姿...",
                  "[文章]一批没有归属感的内容",
                  "[图集]用摄影记录生命 用胶片镌刻青春",
                  "[视频]用镜头刻下你们的点点滴滴 时光之...",
                  "[视频]特斯拉 Model X 试驾...",
                  "[文章]阻止了Wannacry的黑客被逮捕，司法辩护也能众筹",
                  "[科技]腾讯有个叫微粒贷的赚钱机器，凶猛……",
                  "[图集]内蒙古要建一个能折叠、在水面任意“游动”，还可当电影院的行人天桥",
                  "[文章]郎咸平的两个本命年：大运年和坎儿年",
                  "[视频]任天堂Switch的成功，是否意味着“模块化设备”才是未来？"],
    
    "avatarUrls" : ["http://img2.woyaogexing.com/2017/07/14/6bccd9bf2b30c2bf!400x400_big.jpg",
                    "http://img2.woyaogexing.com/2017/07/14/dd8e005b7868f418!400x400_big.jpg",
                    "http://img2.woyaogexing.com/2017/07/14/e2a097437a5f6a81!400x400_big.jpg",
                    "http://img2.woyaogexing.com/2017/07/14/9bff8aceaaf2dfb7!400x400_big.jpg",
                    "http://img2.woyaogexing.com/2017/07/14/06ba5bf0ea0ed23a!400x400_big.jpg",
                    "http://img2.woyaogexing.com/2017/07/14/ddb6039b37aaf9f5!400x400_big.jpg",
                    "http://img2.woyaogexing.com/2017/07/14/50e281285fe269af!400x400_big.jpg",
                    "http://img2.woyaogexing.com/2017/07/14/c2170f25f21607d2!400x400_big.jpg",
                    "http://img2.woyaogexing.com/2017/07/14/9e8862f5518251ec!400x400_big.jpg",
                    "http://img2.woyaogexing.com/2017/07/14/7492200f2f1cb879!400x400_big.jpg",
                    "http://img2.woyaogexing.com/2017/07/14/388925b6a1e1f8e2!400x400_big.jpg",
                    "http://img2.woyaogexing.com/2017/07/14/2c3aab48f453631c!400x400_big.jpg",
                    "http://img2.woyaogexing.com/2017/07/14/612987e9faf7c3cb!400x400_big.jpg",
                    "http://img2.woyaogexing.com/2017/07/14/d6028303c57a1601!400x400_big.jpg",
                    "http://img2.woyaogexing.com/2017/07/14/ea89c2b09afcfa30!400x400_big.jpg"],
    
    "titles" : ["大疆最小自拍无人机 Spark 发布，比 Mavic Pro 还好用？","以后不用缴电费了？特斯拉发布太阳能电池板","消灭堵车的终极方式，除了飞天还能挖隧道","苹果 HomePod 智能音箱终亮相，可它长得有点奇怪？"],
    
    "releaseTimes" : ["刚刚", "10分钟前", "3小时前", "今天 1:00", "昨天 3:00", "昨天 5:44", "前天 4:45", "3天前", "2天前", "5天前","15分钟前","18分钟前","今天 8:24","今天 12:24","今天 10:32", "昨天 6:01", "昨天 5:23", "昨天 4:11"],
    
    "contentDescriptions" : ["存银行定期一年一万块，十年后再去支取，会发生什么？",
                           "深圳60岁老漂创业月入10万 帮儿子缓解房贷压力",
                           "这个女人“救”了刘强东两次，京东的强大有她一半功劳",
                           "中国最有钱的6个女人，个个身价超过百亿",
                           "金融工作会议部署陆续落地，一行三会与金稳会格局渐明",
                           "央企将分三类 规模减至80余家",
                           "打麻将并不能全靠运气，用上这几个技巧或许赢更多",
                           "谁将是下一个投资风口，谁又将接任雄安新区.",
                           "山西首富散尽上百亿家产，但其下员工称其是一位好老板！",
                           "楼市“重磅炸弹”！刚刚，广州宣布“租购同权”",
                           "贾跃亭在美国的31天：融资未获进展，员工不断离职",
                           "首富们的医疗赌注，提示我们必须抓住的三大资源",
                             "亚马逊人工智能布局背后，希望随时随地向你卖东西",
                             "分叉后一周，比特币价格连创新高，竞争币BCC价格腰斩",
                             "爆料大神放出第三方手机壳照，证实iPhone 8全面屏设计",
                             "苹果中国启动“返校优惠”活动，北京直营店除外",
                             "FANG都“弱爆”了？这些中国科技股今年涨幅惊人！",
                             "乐视控股8000万工资款遭招商银行冻结，按时发放仍存悬念",
                             "e袋洗85后CEO陆文勇辞职，即将创业新零售"],
    
    "contentImages" : ["https://pic.36krcnd.com/avatar/201707/17062437/qvgwzfonfy4p1mfc.jpg!heading",
                     "https://pic.36krcnd.com/avatar/201707/24024652/3jyqzlawqew2d4eo.jpeg!heading",
                     "https://pic.36krcnd.com/avatar/201707/24054844/6lub9ocv7cnpp2b0.png!heading",
                     "https://pic.36krcnd.com/avatar/201707/24053513/yv3bqzitysc6bmu0.jpg!heading",
                     "https://pic.36krcnd.com/avatar/201707/18101720/r8ndchj8iibbfkf8.jpg!heading",
                     "https://pic.36krcnd.com/avatar/201707/20150812/xtm0lizftb4pm95u.jpg!heading",
                     "https://pic.36krcnd.com/avatar/201707/24043449/my6afv4q9bf3ney5.png!heading",
                       "https://pic.36krcnd.com/201708/08020238/r8e1unj9pcliv113!1200",
                       "https://pic.36krcnd.com/avatar/201708/08023207/0zwlat8b1sgoy30o.jpg!1200",
                       "https://pic.36krcnd.com/avatar/201708/08041208/k5dnhgqlt1h44836.jpg!1200",
                       "https://pic.36krcnd.com/avatar/201708/07095558/qiqb91t2e1lou1me.png!1200",
                       "https://pic.36krcnd.com/201708/08053057/2kch8rv9b7uh363f!1200",
                       "https://pic.36krcnd.com/201708/08053057/v8ymy646vbwwe3ni!1200",
                       "https://pic.36krcnd.com/201708/08053057/qavcyah6ztq51tnn!1200",
                       "https://pic.36krcnd.com/avatar/201708/08052440/ap8hup49lcu70b2y.jpg!1200",
                       "https://pic.36krcnd.com/avatar/201708/08063122/p58wyque3kiu33ox.jpg!1200",
                       "https://pic.36krcnd.com/avatar/201708/08063247/b7iza44vrf5b6bzb.jpg!1200",
                       "https://pic.36krcnd.com/avatar/201708/08091101/myp0tv3ym7vjhck3.jpg!1200",
                       "https://pic.36krcnd.com/avatar/201708/08043614/aqp68zk8f4nzdtrj.jpg!1200"],
    
    "durations" : ["3'15\"", "2'15\"", "4'22\"", "3'16\"", "3'56\"", "4'34\"", "1'16\"", "2'31\""],
    
    "videos" : ["http://baobab.wdjcdn.com/14564977406580.mp4",
                "http://storage.gzstv.net/uploads/media/huangmeiyan/jr05-09.mp4"],
    
    "activitTimes" : ["4/28 07:00-19:30",
                     "4/28 09:00-17:30",
                     "3/18 10:00-12:30",
                     "2/10 11:00-20:30",
                     "7/15 12:00-21:30",
                     "8/26 17:00-22:30",
                     "6/05 13:00-19:30"],
    
    "activityAmounts" : ["免费",
                         "￥168-￥1388",
                        "￥500-￥1994",
                        "￥1000-￥4992",
                        "￥100-￥1348",
                        "￥1485-￥9472",
                        "￥492-￥1238"],
    
    "lifeLocations" : ["广东深圳", "广东广州", "辽宁铁岭", "四川成都", "山西太原"],
    "introduces" : ["靡不有初鲜克有终","谁终将声震人间，比长久深自缄默","吾日三省吾身","明月别枝惊鹊，清风半夜鸣蝉","咨询走值乎","魔性多汁 好吃贼辣","文艺流氓，情趣玩家，纯洁司机，爱好颇多，嬉而不精。已开通值乎。","无知的所知","☀️高能预警 禁止点击！","为你揭开隐藏于冰山水面下的数据秘密","我本是卧龙岗旁那闲散的人","爱吃能吃的小可爱","我是保守主义者，简单来说就是精赵，谢谢。","特别认真/生活是一门艺术","我慢慢写，你慢慢读。","让灵魂变美的，是灵魂，而不是书籍","属于8%的那一小撮","神经质的准铲屎官","繁华落尽与君老"]
}
